{
  "wildCardIndicator": true,
  "standingsDateTimeUtc": "2026-04-09T16:55:51Z",
  "standings": [
    {
      "conferenceAbbrev": "W",
      "conferenceHomeSequence": 1,
      "conferenceL10Sequence": 1,
      "conferenceName": "Western",
      "conferenceRoadSequence": 3,
      "conferenceSequence": 1,
      "date": "2025-12-04",
      "divisionAbbrev": "C",
      "divisionHomeSequence": 1,
      "divisionL10Sequence": 1,
      "divisionName": "Central",
      "divisionRoadSequence": 2,
      "divisionSequence": 1,
      "gameTypeId": 2,
      "gamesPlayed": 27,
      "goalDifferential": 47,
      "goalDifferentialPctg": 1.740741,
      "goalAgainst": 62,
      "goalFor": 109,
      "goalsForPctg": 4.037037,
      "homeGamesPlayed": 13,
      "homeGoalDifferential": 32,
      "homeGoalsAgainst": 29,
      "homeGoalsFor": 61,
      "homeLosses": 0,
      "homeOtLosses": 2,
      "homePoints": 24,
      "homeRegulationPlusOtWins": 11,
      "homeRegulationWins": 11,
      "homeTies": 0,
      "homeWins": 11,
      "l10GamesPlayed": 10,
      "l10GoalDifferential": 22,
      "l10GoalsAgainst": 19,
      "l10GoalsFor": 41,
      "l10Losses": 1,
      "l10OtLosses": 1,
      "l10Points": 17,
      "l10RegulationPlusOtWins": 8,
      "l10RegulationWins": 8,
      "l10Ties": 0,
      "l10Wins": 8,
      "leagueHomeSequence": 1,
      "leagueL10Sequence": 2,
      "leagueRoadSequence": 4,
      "leagueSequence": 1,
      "losses": 2,
      "otLosses": 6,
      "placeName": {
        "default": "Colorado"
      },
      "pointPctg": 0.814815,
      "points": 44,
      "regulationPlusOtWinPctg": 0.703704,
      "regulationPlusOtWins": 19,
      "regulationWinPctg": 0.666667,
      "regulationWins": 18,
      "roadGamesPlayed": 14,
      "roadGoalDifferential": 15,
      "roadGoalsAgainst": 33,
      "roadGoalsFor": 48,
      "roadLosses": 2,
      "roadOtLosses": 4,
      "roadPoints": 20,
      "roadRegulationPlusOtWins": 8,
      "roadRegulationWins": 7,
      "roadTies": 0,
      "roadWins": 8,
      "seasonId": 20252026,
      "shootoutLosses": 3,
      "shootoutWins": 0,
      "streakCode": "L",
      "streakCount": 1,
      "teamName": {
        "default": "Colorado Avalanche",
        "fr": "Avalanche du Colorado"
      },
      "teamCommonName": {
        "default": "Avalanche"
      },
      "teamAbbrev": {
        "default": "COL"
      },
      "teamLogo": "https://assets.nhle.com/logos/nhl/svg/COL_light.svg",
      "ties": 0,
      "waiversSequence": 32,
      "wildcardSequence": 0,
      "winPctg": 0.703704,
      "wins": 19
    },
    {
      "conferenceAbbrev": "W",
      "conferenceHomeSequence": 6,
      "conferenceL10Sequence": 3,
      "conferenceName": "Western",
      "conferenceRoadSequence": 1,
      "conferenceSequence": 2,
      "date": "2025-12-04",
      "divisionAbbrev": "C",
      "divisionHomeSequence": 3,
      "divisionL10Sequence": 3,
      "divisionName": "Central",
      "divisionRoadSequence": 1,
      "divisionSequence": 2,
      "gameTypeId": 2,
      "gamesPlayed": 28,
      "goalDifferential": 24,
      "goalDifferentialPctg": 0.857143,
      "goalAgainst": 74,
      "goalFor": 98,
      "goalsForPctg": 3.5,
      "homeGamesPlayed": 13,
      "homeGoalDifferential": 7,
      "homeGoalsAgainst": 36,
      "homeGoalsFor": 43,
      "homeLosses": 4,
      "homeOtLosses": 1,
      "homePoints": 17,
      "homeRegulationPlusOtWins": 7,
      "homeRegulationWins": 7,
      "homeTies": 0,
      "homeWins": 8,
      "l10GamesPlayed": 10,
      "l10GoalDifferential": 18,
      "l10GoalsAgainst": 21,
      "l10GoalsFor": 39,
      "l10Losses": 1,
      "l10OtLosses": 2,
      "l10Points": 16,
      "l10RegulationPlusOtWins": 7,
      "l10RegulationWins": 7,
      "l10Ties": 0,
      "l10Wins": 7,
      "leagueHomeSequence": 14,
      "leagueL10Sequence": 4,
      "leagueRoadSequence": 2,
      "leagueSequence": 2,
      "losses": 5,
      "otLosses": 5,
      "placeName": {
        "default": "Dallas"
      },
      "pointPctg": 0.732143,
      "points": 41,
      "regulationPlusOtWinPctg": 0.571429,
      "regulationPlusOtWins": 16,
      "regulationWinPctg": 0.535714,
      "regulationWins": 15,
      "roadGamesPlayed": 15,
      "roadGoalDifferential": 17,
      "roadGoalsAgainst": 38,
      "roadGoalsFor": 55,
      "roadLosses": 1,
      "roadOtLosses": 4,
      "roadPoints": 24,
      "roadRegulationPlusOtWins": 9,
      "roadRegulationWins": 8,
      "roadTies": 0,
      "roadWins": 10,
      "seasonId": 20252026,
      "shootoutLosses": 2,
      "shootoutWins": 2,
      "streakCode": "W",
      "streakCount": 1,
      "teamName": {
        "default": "Dallas Stars",
        "fr": "Stars de Dallas"
      },
      "teamCommonName": {
        "default": "Stars"
      },
      "teamAbbrev": {
        "default": "DAL"
      },
      "teamLogo": "https://assets.nhle.com/logos/nhl/svg/DAL_light.svg",
      "ties": 0,
      "waiversSequence": 31,
      "wildcardSequence": 0,
      "winPctg": 0.642857,
      "wins": 18
    },
    {
      "conferenceAbbrev": "E",
      "conferenceHomeSequence": 5,
      "conferenceL10Sequence": 1,
      "conferenceName": "Eastern",
      "conferenceRoadSequence": 4,
      "conferenceSequence": 1,
      "date": "2025-12-04",
      "divisionAbbrev": "M",
      "divisionHomeSequence": 3,
      "divisionL10Sequence": 1,
      "divisionName": "Metropolitan",
      "divisionRoadSequence": 3,
      "divisionSequence": 1,
      "gameTypeId": 2,
      "gamesPlayed": 28,
      "goalDifferential": 27,
      "goalDifferentialPctg": 0.964286,
      "goalAgainst": 71,
      "goalFor": 98,
      "goalsForPctg": 3.5,
      "homeGamesPlayed": 15,
      "homeGoalDifferential": 10,
      "homeGoalsAgainst": 41,
      "homeGoalsFor": 51,
      "homeLosses": 5,
      "homeOtLosses": 1,
      "homePoints": 19,
      "homeRegulationPlusOtWins": 9,
      "homeRegulationWins": 8,
      "homeTies": 0,
      "homeWins": 9,
      "l10GamesPlayed": 10,
      "l10GoalDifferential": 24,
      "l10GoalsAgainst": 23,
      "l10GoalsFor": 47,
      "l10Losses": 1,
      "l10OtLosses": 0,
      "l10Points": 18,
      "l10RegulationPlusOtWins": 9,
      "l10RegulationWins": 9,
      "l10Ties": 0,
      "l10Wins": 9,
      "leagueHomeSequence": 8,
      "leagueL10Sequence": 1,
      "leagueRoadSequence": 7,
      "leagueSequence": 3,
      "losses": 9,
      "otLosses": 2,
      "placeName": {
        "default": "Washington"
      },
      "pointPctg": 0.642857,
      "points": 36,
      "regulationPlusOtWinPctg": 0.607143,
      "regulationPlusOtWins": 17,
      "regulationWinPctg": 0.571429,
      "regulationWins": 16,
      "roadGamesPlayed": 13,
      "roadGoalDifferential": 17,
      "roadGoalsAgainst": 30,
      "roadGoalsFor": 47,
      "roadLosses": 4,
      "roadOtLosses": 1,
      "roadPoints": 17,
      "roadRegulationPlusOtWins": 8,
      "roadRegulationWins": 8,
      "roadTies": 0,
      "roadWins": 8,
      "seasonId": 20252026,
      "shootoutLosses": 2,
      "shootoutWins": 0,
      "streakCode": "W",
      "streakCount": 6,
      "teamName": {
        "default": "Washington Capitals",
        "fr": "Capitals de Washington"
      },
      "teamCommonName": {
        "default": "Capitals"
      },
      "teamAbbrev": {
        "default": "WSH"
      },
      "teamLogo": "https://assets.nhle.com/logos/nhl/svg/WSH_secondary_light.svg",
      "ties": 0,
      "waiversSequence": 29,
      "wildcardSequence": 0,
      "winPctg": 0.607143,
      "wins": 17
    },
    {
      "conferenceAbbrev": "W",
      "conferenceHomeSequence": 3,
      "conferenceL10Sequence": 2,
      "conferenceName": "Western",
      "conferenceRoadSequence": 5,
      "conferenceSequence": 3,
      "date": "2025-12-04",
      "divisionAbbrev": "C",
      "divisionHomeSequence": 2,
      "divisionL10Sequence": 2,
      "divisionName": "Central",
      "divisionRoadSequence": 3,
      "divisionSequence": 3,
      "gameTypeId": 2,
      "gamesPlayed": 28,
      "goalDifferential": 3,
      "goalDifferentialPctg": 0.107143,
      "goalAgainst": 76,
      "goalFor": 79,
      "goalsForPctg": 2.821429,
      "homeGamesPlayed": 15,
      "homeGoalDifferential": -2,
      "homeGoalsAgainst": 46,
      "homeGoalsFor": 44,
      "homeLosses": 3,
      "homeOtLosses": 4,
      "homePoints": 20,
      "homeRegulationPlusOtWins": 5,
      "homeRegulationWins": 3,
      "homeTies": 0,
      "homeWins": 8,
      "l10GamesPlayed": 10,
      "l10GoalDifferential": 11,
      "l10GoalsAgainst": 17,
      "l10GoalsFor": 28,
      "l10Losses": 1,
      "l10OtLosses": 1,
      "l10Points": 17,
      "l10RegulationPlusOtWins": 6,
      "l10RegulationWins": 4,
      "l10Ties": 0,
      "l10Wins": 8,
      "leagueHomeSequence": 5,
      "leagueL10Sequence": 3,
      "leagueRoadSequence": 14,
      "leagueSequence": 4,
      "losses": 8,
      "otLosses": 5,
      "placeName": {
        "default": "Minnesota"
      },
      "pointPctg": 0.625,
      "points": 35,
      "regulationPlusOtWinPctg": 0.428571,
      "regulationPlusOtWins": 12,
      "regulationWinPctg": 0.321429,
      "regulationWins": 9,
      "roadGamesPlayed": 13,
      "roadGoalDifferential": 5,
      "roadGoalsAgainst": 30,
      "roadGoalsFor": 35,
      "roadLosses": 5,
      "roadOtLosses": 1,
      "roadPoints": 15,
      "roadRegulationPlusOtWins": 7,
      "roadRegulationWins": 6,
      "roadTies": 0,
      "roadWins": 7,
      "seasonId": 20252026,
      "shootoutLosses": 1,
      "shootoutWins": 3,
      "streakCode": "L",
      "streakCount": 1,
      "teamName": {
        "default": "Minnesota Wild",
        "fr": "Wild du Minnesota"
      },
      "teamCommonName": {
        "default": "Wild"
      },
      "teamAbbrev": {
        "default": "MIN"
      },
      "teamLogo": "https://assets.nhle.com/logos/nhl/svg/MIN_light.svg",
      "ties": 0,
      "waiversSequence": 25,
      "wildcardSequence": 0,
      "winPctg": 0.535714,
      "wins": 15
    },
    {
      "conferenceAbbrev": "E",
      "conferenceHomeSequence": 9,
      "conferenceL10Sequence": 7,
      "conferenceName": "Eastern",
      "conferenceRoadSequence": 5,
      "conferenceSequence": 2,
      "date": "2025-12-04",
      "divisionAbbrev": "M",
      "divisionHomeSequence": 4,
      "divisionL10Sequence": 4,
      "divisionName": "Metropolitan",
      "divisionRoadSequence": 4,
      "divisionSequence": 2,
      "gameTypeId": 2,
      "gamesPlayed": 26,
      "goalDifferential": 12,
      "goalDifferentialPctg": 0.461538,
      "goalAgainst": 75,
      "goalFor": 87,
      "goalsForPctg": 3.346154,
      "homeGamesPlayed": 13,
      "homeGoalDifferential": 5,
      "homeGoalsAgainst": 41,
      "homeGoalsFor": 46,
      "homeLosses": 4,
      "homeOtLosses": 1,
      "homePoints": 17,
      "homeRegulationPlusOtWins": 8,
      "homeRegulationWins": 5,
      "homeTies": 0,
      "homeWins": 8,
      "l10GamesPlayed": 10,
      "l10GoalDifferential": -2,
      "l10GoalsAgainst": 29,
      "l10GoalsFor": 27,
      "l10Losses": 3,
      "l10OtLosses": 2,
      "l10Points": 12,
      "l10RegulationPlusOtWins": 5,
      "l10RegulationWins": 3,
      "l10Ties": 0,
      "l10Wins": 5,
      "leagueHomeSequence": 15,
      "leagueL10Sequence": 12,
      "leagueRoadSequence": 8,
      "leagueSequence": 5,
      "losses": 8,
      "otLosses": 2,
      "placeName": {
        "default": "Carolina",
        "fr": "Caroline"
      },
      "pointPctg": 0.653846,
      "points": 34,
      "regulationPlusOtWinPctg": 0.576923,
      "regulationPlusOtWins": 15,
      "regulationWinPctg": 0.423077,
      "regulationWins": 11,
      "roadGamesPlayed": 13,
      "roadGoalDifferential": 7,
      "roadGoalsAgainst": 34,
      "roadGoalsFor": 41,
      "roadLosses": 4,
      "roadOtLosses": 1,
      "roadPoints": 17,
      "roadRegulationPlusOtWins": 7,
      "roadRegulationWins": 6,
      "roadTies": 0,
      "roadWins": 8,
      "seasonId": 20252026,
      "shootoutLosses": 1,
      "shootoutWins": 1,
      "streakCode": "L",
      "streakCount": 1,
      "teamName": {
        "default": "Carolina Hurricanes",
        "fr": "Hurricanes de la Caroline"
      },
      "teamCommonName": {
        "default": "Hurricanes"
      },
      "teamAbbrev": {
        "default": "CAR"
      },
      "teamLogo": "https://assets.nhle.com/logos/nhl/svg/CAR_light.svg",
      "ties": 0,
      "waiversSequence": 30,
      "wildcardSequence": 0,
      "winPctg": 0.615385,
      "wins": 16
    },
    {
      "conferenceAbbrev": "E",
      "conferenceHomeSequence": 10,
      "conferenceL10Sequence": 2,
      "conferenceName": "Eastern",
      "conferenceRoadSequence": 3,
      "conferenceSequence": 3,
      "date": "2025-12-04",
      "divisionAbbrev": "A",
      "divisionHomeSequence": 6,
      "divisionL10Sequence": 1,
      "divisionName": "Atlantic",
      "divisionRoadSequence": 1,
      "divisionSequence": 1,
      "gameTypeId": 2,
      "gamesPlayed": 27,
      "goalDifferential": 17,
      "goalDifferentialPctg": 0.62963,
      "goalAgainst": 71,
      "goalFor": 88,
      "goalsForPctg": 3.259259,
      "homeGamesPlayed": 14,
      "homeGoalDifferential": 3,
      "homeGoalsAgainst": 40,
      "homeGoalsFor": 43,
      "homeLosses": 6,
      "homeOtLosses": 0,
      "homePoints": 16,
      "homeRegulationPlusOtWins": 8,
      "homeRegulationWins": 5,
      "homeTies": 0,
      "homeWins": 8,
      "l10GamesPlayed": 10,
      "l10GoalDifferential": 14,
      "l10GoalsAgainst": 22,
      "l10GoalsFor": 36,
      "l10Losses": 3,
      "l10OtLosses": 0,
      "l10Points": 14,
      "l10RegulationPlusOtWins": 7,
      "l10RegulationWins": 6,
      "l10Ties": 0,
      "l10Wins": 7,
      "leagueHomeSequence": 16,
      "leagueL10Sequence": 5,
      "leagueRoadSequence": 6,
      "leagueSequence": 6,
      "losses": 9,
      "otLosses": 2,
      "placeName": {
        "default": "Tampa Bay"
      },
      "pointPctg": 0.62963,
      "points": 34,
      "regulationPlusOtWinPctg": 0.592593,
      "regulationPlusOtWins": 16,
      "regulationWinPctg": 0.481481,
      "regulationWins": 13,
      "roadGamesPlayed": 13,
      "roadGoalDifferential": 14,
      "roadGoalsAgainst": 31,
      "roadGoalsFor": 45,
      "roadLosses": 3,
      "roadOtLosses": 2,
      "roadPoints": 18,
      "roadRegulationPlusOtWins": 8,
      "roadRegulationWins": 8,
      "roadTies": 0,
      "roadWins": 8,
      "seasonId": 20252026,
      "shootoutLosses": 0,
      "shootoutWins": 0,
      "streakCode": "L",
      "streakCount": 2,
      "teamName": {
        "default": "Tampa Bay Lightning",
        "fr": "Lightning de Tampa Bay"
      },
      "teamCommonName": {
        "default": "Lightning"
      },
      "teamAbbrev": {
        "default": "TBL"
      },
      "teamLogo": "https://assets.nhle.com/logos/nhl/svg/TBL_light.svg",
      "ties": 0,
      "waiversSequence": 26,
      "wildcardSequence": 0,
      "winPctg": 0.592593,
      "wins": 16
    },
    {
      "conferenceAbbrev": "E",
      "conferenceHomeSequence": 14,
      "conferenceL10Sequence": 5,
      "conferenceName": "Eastern",
      "conferenceRoadSequence": 2,
      "conferenceSequence": 4,
      "date": "2025-12-04",
      "divisionAbbrev": "M",
      "divisionHomeSequence": 7,
      "divisionL10Sequence": 3,
      "divisionName": "Metropolitan",
      "divisionRoadSequence": 2,
      "divisionSequence": 3,
      "gameTypeId": 2,
      "gamesPlayed": 26,
      "goalDifferential": 9,
      "goalDifferentialPctg": 0.346154,
      "goalAgainst": 74,
      "goalFor": 83,
      "goalsForPctg": 3.192308,
      "homeGamesPlayed": 12,
      "homeGoalDifferential": -2,
      "homeGoalsAgainst": 41,
      "homeGoalsFor": 39,
      "homeLosses": 4,
      "homeOtLosses": 2,
      "homePoints": 14,
      "homeRegulationPlusOtWins": 6,
      "homeRegulationWins": 6,
      "homeTies": 0,
      "homeWins": 6,
      "l10GamesPlayed": 10,
      "l10GoalDifferential": -1,
      "l10GoalsAgainst": 29,
      "l10GoalsFor": 28,
      "l10Losses": 3,
      "l10OtLosses": 2,
      "l10Points": 12,
      "l10RegulationPlusOtWins": 5,
      "l10RegulationWins": 4,
      "l10Ties": 0,
      "l10Wins": 5,
      "leagueHomeSequence": 24,
      "leagueL10Sequence": 9,
      "leagueRoadSequence": 5,
      "leagueSequence": 7,
      "losses": 7,
      "otLosses": 5,
      "placeName": {
        "default": "Pittsburgh"
      },
      "pointPctg": 0.634615,
      "points": 33,
      "regulationPlusOtWinPctg": 0.538462,
      "regulationPlusOtWins": 14,
      "regulationWinPctg": 0.5,
      "regulationWins": 13,
      "roadGamesPlayed": 14,
      "roadGoalDifferential": 11,
      "roadGoalsAgainst": 33,
      "roadGoalsFor": 44,
      "roadLosses": 3,
      "roadOtLosses": 3,
      "roadPoints": 19,
      "roadRegulationPlusOtWins": 8,
      "roadRegulationWins": 7,
      "roadTies": 0,
      "roadWins": 8,
      "seasonId": 20252026,
      "shootoutLosses": 3,
      "shootoutWins": 0,
      "streakCode": "W",
      "streakCount": 2,
      "teamName": {
        "default": "Pittsburgh Penguins",
        "fr": "Penguins de Pittsburgh"
      },
      "teamCommonName": {
        "default": "Penguins"
      },
      "teamAbbrev": {
        "default": "PIT"
      },
      "teamLogo": "https://assets.nhle.com/logos/nhl/svg/PIT_light.svg",
      "ties": 0,
      "waiversSequence": 28,
      "wildcardSequence": 0,
      "winPctg": 0.538462,
      "wins": 14
    },
    {
      "conferenceAbbrev": "E",
      "conferenceHomeSequence": 2,
      "conferenceL10Sequence": 3,
      "conferenceName": "Eastern",
      "conferenceRoadSequence": 11,
      "conferenceSequence": 5,
      "date": "2025-12-04",
      "divisionAbbrev": "M",
      "divisionHomeSequence": 1,
      "divisionL10Sequence": 2,
      "divisionName": "Metropolitan",
      "divisionRoadSequence": 8,
      "divisionSequence": 4,
      "gameTypeId": 2,
      "gamesPlayed": 26,
      "goalDifferential": 5,
      "goalDifferentialPctg": 0.192308,
      "goalAgainst": 74,
      "goalFor": 79,
      "goalsForPctg": 3.038462,
      "homeGamesPlayed": 15,
      "homeGoalDifferential": 6,
      "homeGoalsAgainst": 40,
      "homeGoalsFor": 46,
      "homeLosses": 4,
      "homeOtLosses": 2,
      "homePoints": 20,
      "homeRegulationPlusOtWins": 7,
      "homeRegulationWins": 5,
      "homeTies": 0,
      "homeWins": 9,
      "l10GamesPlayed": 10,
      "l10GoalDifferential": 2,
      "l10GoalsAgainst": 33,
      "l10GoalsFor": 35,
      "l10Losses": 3,
      "l10OtLosses": 0,
      "l10Points": 14,
      "l10RegulationPlusOtWins": 5,
      "l10RegulationWins": 4,
      "l10Ties": 0,
      "l10Wins": 7,
      "leagueHomeSequence": 4,
      "leagueL10Sequence": 6,
      "leagueRoadSequence": 22,
      "leagueSequence": 8,
      "losses": 8,
      "otLosses": 3,
      "placeName": {
        "default": "Philadelphia",
        "fr": "Philadelphie"
      },
      "pointPctg": 0.634615,
      "points": 33,
      "regulationPlusOtWinPctg": 0.384615,
      "regulationPlusOtWins": 10,
      "regulationWinPctg": 0.307692,
      "regulationWins": 8,
      "roadGamesPlayed": 11,
      "roadGoalDifferential": -1,
      "roadGoalsAgainst": 34,
      "roadGoalsFor": 33,
      "roadLosses": 4,
      "roadOtLosses": 1,
      "roadPoints": 13,
      "roadRegulationPlusOtWins": 3,
      "roadRegulationWins": 3,
      "roadTies": 0,
      "roadWins": 6,
      "seasonId": 20252026,
      "shootoutLosses": 0,
      "shootoutWins": 5,
      "streakCode": "W",
      "streakCount": 1,
      "teamName": {
        "default": "Philadelphia Flyers",
        "fr": "Flyers de Philadelphie"
      },
      "teamCommonName": {
        "default": "Flyers"
      },
      "teamAbbrev": {
        "default": "PHI"
      },
      "teamLogo": "https://assets.nhle.com/logos/nhl/svg/PHI_light.svg",
      "ties": 0,
      "waiversSequence": 27,
      "wildcardSequence": 1,
      "winPctg": 0.576923,
      "wins": 15
    },
    {
      "conferenceAbbrev": "W",
      "conferenceHomeSequence": 4,
      "conferenceL10Sequence": 11,
      "conferenceName": "Western",
      "conferenceRoadSequence": 7,
      "conferenceSequence": 4,
      "date": "2025-12-04",
      "divisionAbbrev": "P",
      "divisionHomeSequence": 2,
      "divisionL10Sequence": 6,
      "divisionName": "Pacific",
      "divisionRoadSequence": 3,
      "divisionSequence": 1,
      "gameTypeId": 2,
      "gamesPlayed": 27,
      "goalDifferential": 5,
      "goalDifferentialPctg": 0.185185,
      "goalAgainst": 91,
      "goalFor": 96,
      "goalsForPctg": 3.555556,
      "homeGamesPlayed": 13,
      "homeGoalDifferential": 6,
      "homeGoalsAgainst": 41,
      "homeGoalsFor": 47,
      "homeLosses": 4,
      "homeOtLosses": 0,
      "homePoints": 18,
      "homeRegulationPlusOtWins": 8,
      "homeRegulationWins": 6,
      "homeTies": 0,
      "homeWins": 9,
      "l10GamesPlayed": 10,
      "l10GoalDifferential": -6,
      "l10GoalsAgainst": 35,
      "l10GoalsFor": 29,
      "l10Losses": 5,
      "l10OtLosses": 0,
      "l10Points": 10,
      "l10RegulationPlusOtWins": 4,
      "l10RegulationWins": 2,
      "l10Ties": 0,
      "l10Wins": 5,
      "leagueHomeSequence": 11,
      "leagueL10Sequence": 24,
      "leagueRoadSequence": 16,
      "leagueSequence": 9,
      "losses": 10,
      "otLosses": 1,
      "placeName": {
        "default": "Anaheim"
      },
      "pointPctg": 0.611111,
      "points": 33,
      "regulationPlusOtWinPctg": 0.518519,
      "regulationPlusOtWins": 14,
      "regulationWinPctg": 0.37037,
      "regulationWins": 10,
      "roadGamesPlayed": 14,
      "roadGoalDifferential": -1,
      "roadGoalsAgainst": 50,
      "roadGoalsFor": 49,
      "roadLosses": 6,
      "roadOtLosses": 1,
      "roadPoints": 15,
      "roadRegulationPlusOtWins": 6,
      "roadRegulationWins": 4,
      "roadTies": 0,
      "roadWins": 7,
      "seasonId": 20252026,
      "shootoutLosses": 0,
      "shootoutWins": 2,
      "streakCode": "L",
      "streakCount": 1,
      "teamName": {
        "default": "Anaheim Ducks",
        "fr": "Ducks d'Anaheim"
      },
      "teamCommonName": {
        "default": "Ducks"
      },
      "teamAbbrev": {
        "default": "ANA"
      },
      "teamLogo": "https://assets.nhle.com/logos/nhl/svg/ANA_light.svg",
      "ties": 0,
      "waiversSequence": 23,
      "wildcardSequence": 0,
      "winPctg": 0.592593,
      "wins": 16
    },
    {
      "conferenceAbbrev": "E",
      "conferenceHomeSequence": 4,
      "conferenceL10Sequence": 16,
      "conferenceName": "Eastern",
      "conferenceRoadSequence": 10,
      "conferenceSequence": 6,
      "date": "2025-12-04",
      "divisionAbbrev": "M",
      "divisionHomeSequence": 2,
      "divisionL10Sequence": 8,
      "divisionName": "Metropolitan",
      "divisionRoadSequence": 7,
      "divisionSequence": 5,
      "gameTypeId": 2,
      "gamesPlayed": 27,
      "goalDifferential": 1,
      "goalDifferentialPctg": 0.037037,
      "goalAgainst": 82,
      "goalFor": 83,
      "goalsForPctg": 3.074074,
      "homeGamesPlayed": 13,
      "homeGoalDifferential": 6,
      "homeGoalsAgainst": 34,
      "homeGoalsFor": 40,
      "homeLosses": 3,
      "homeOtLosses": 1,
      "homePoints": 19,
      "homeRegulationPlusOtWins": 8,
      "homeRegulationWins": 5,
      "homeTies": 0,
      "homeWins": 9,
      "l10GamesPlayed": 10,
      "l10GoalDifferential": -7,
      "l10GoalsAgainst": 32,
      "l10GoalsFor": 25,
      "l10Losses": 6,
      "l10OtLosses": 0,
      "l10Points": 8,
      "l10RegulationPlusOtWins": 3,
      "l10RegulationWins": 2,
      "l10Ties": 0,
      "l10Wins": 4,
      "leagueHomeSequence": 7,
      "leagueL10Sequence": 30,
      "leagueRoadSequence": 20,
      "leagueSequence": 10,
      "losses": 10,
      "otLosses": 1,
      "placeName": {
        "default": "New Jersey"
      },
      "pointPctg": 0.611111,
      "points": 33,
      "regulationPlusOtWinPctg": 0.518519,
      "regulationPlusOtWins": 14,
      "regulationWinPctg": 0.37037,
      "regulationWins": 10,
      "roadGamesPlayed": 14,
      "roadGoalDifferential": -5,
      "roadGoalsAgainst": 48,
      "roadGoalsFor": 43,
      "roadLosses": 7,
      "roadOtLosses": 0,
      "roadPoints": 14,
      "roadRegulationPlusOtWins": 6,
      "roadRegulationWins": 5,
      "roadTies": 0,
      "roadWins": 7,
      "seasonId": 20252026,
      "shootoutLosses": 0,
      "shootoutWins": 2,
      "streakCode": "L",
      "streakCount": 3,
      "teamName": {
        "default": "New Jersey Devils",
        "fr": "Devils du New Jersey"
      },
      "teamCommonName": {
        "default": "Devils"
      },
      "teamAbbrev": {
        "default": "NJD"
      },
      "teamLogo": "https://assets.nhle.com/logos/nhl/svg/NJD_light.svg",
      "ties": 0,
      "waiversSequence": 22,
      "wildcardSequence": 2,
      "winPctg": 0.592593,
      "wins": 16
    },
    {
      "conferenceAbbrev": "E",
      "conferenceHomeSequence": 11,
      "conferenceL10Sequence": 9,
      "conferenceName": "Eastern",
      "conferenceRoadSequence": 6,
      "conferenceSequence": 7,
      "date": "2025-12-04",
      "divisionAbbrev": "M",
      "divisionHomeSequence": 5,
      "divisionL10Sequence": 6,
      "divisionName": "Metropolitan",
      "divisionRoadSequence": 5,
      "divisionSequence": 6,
      "gameTypeId": 2,
      "gamesPlayed": 28,
      "goalDifferential": 3,
      "goalDifferentialPctg": 0.107143,
      "goalAgainst": 81,
      "goalFor": 84,
      "goalsForPctg": 3,
      "homeGamesPlayed": 15,
      "homeGoalDifferential": -2,
      "homeGoalsAgainst": 44,
      "homeGoalsFor": 42,
      "homeLosses": 6,
      "homeOtLosses": 2,
      "homePoints": 16,
      "homeRegulationPlusOtWins": 6,
      "homeRegulationWins": 6,
      "homeTies": 0,
      "homeWins": 7,
      "l10GamesPlayed": 10,
      "l10GoalDifferential": 1,
      "l10GoalsAgainst": 23,
      "l10GoalsFor": 24,
      "l10Losses": 4,
      "l10OtLosses": 1,
      "l10Points": 11,
      "l10RegulationPlusOtWins": 4,
      "l10RegulationWins": 4,
      "l10Ties": 0,
      "l10Wins": 5,
      "leagueHomeSequence": 17,
      "leagueL10Sequence": 14,
      "leagueRoadSequence": 9,
      "leagueSequence": 11,
      "losses": 10,
      "otLosses": 3,
      "placeName": {
        "default": "NY Islanders"
      },
      "pointPctg": 0.589286,
      "points": 33,
      "regulationPlusOtWinPctg": 0.5,
      "regulationPlusOtWins": 14,
      "regulationWinPctg": 0.392857,
      "regulationWins": 11,
      "roadGamesPlayed": 13,
      "roadGoalDifferential": 5,
      "roadGoalsAgainst": 37,
      "roadGoalsFor": 42,
      "roadLosses": 4,
      "roadOtLosses": 1,
      "roadPoints": 17,
      "roadRegulationPlusOtWins": 8,
      "roadRegulationWins": 5,
      "roadTies": 0,
      "roadWins": 8,
      "seasonId": 20252026,
      "shootoutLosses": 3,
      "shootoutWins": 1,
      "streakCode": "W",
      "streakCount": 2,
      "teamName": {
        "default": "New York Islanders",
        "fr": "Islanders de New York"
      },
      "teamCommonName": {
        "default": "Islanders"
      },
      "teamAbbrev": {
        "default": "NYI"
      },
      "teamLogo": "https://assets.nhle.com/logos/nhl/svg/NYI_light.svg",
      "ties": 0,
      "waiversSequence": 20,
      "wildcardSequence": 3,
      "winPctg": 0.535714,
      "wins": 15
    },
    {
      "conferenceAbbrev": "W",
      "conferenceHomeSequence": 5,
      "conferenceL10Sequence": 4,
      "conferenceName": "Western",
      "conferenceRoadSequence": 10,
      "conferenceSequence": 5,
      "date": "2025-12-04",
      "divisionAbbrev": "P",
      "divisionHomeSequence": 3,
      "divisionL10Sequence": 1,
      "divisionName": "Pacific",
      "divisionRoadSequence": 5,
      "divisionSequence": 2,
      "gameTypeId": 2,
      "gamesPlayed": 26,
      "goalDifferential": 1,
      "goalDifferentialPctg": 0.038462,
      "goalAgainst": 79,
      "goalFor": 80,
      "goalsForPctg": 3.076923,
      "homeGamesPlayed": 15,
      "homeGoalDifferential": 0,
      "homeGoalsAgainst": 50,
      "homeGoalsFor": 50,
      "homeLosses": 4,
      "homeOtLosses": 4,
      "homePoints": 18,
      "homeRegulationPlusOtWins": 6,
      "homeRegulationWins": 6,
      "homeTies": 0,
      "homeWins": 7,
      "l10GamesPlayed": 10,
      "l10GoalDifferential": -1,
      "l10GoalsAgainst": 30,
      "l10GoalsFor": 29,
      "l10Losses": 2,
      "l10OtLosses": 3,
      "l10Points": 13,
      "l10RegulationPlusOtWins": 4,
      "l10RegulationWins": 4,
      "l10Ties": 0,
      "l10Wins": 5,
      "leagueHomeSequence": 12,
      "leagueL10Sequence": 7,
      "leagueRoadSequence": 19,
      "leagueSequence": 12,
      "losses": 6,
      "otLosses": 8,
      "placeName": {
        "default": "Vegas"
      },
      "pointPctg": 0.615385,
      "points": 32,
      "regulationPlusOtWinPctg": 0.423077,
      "regulationPlusOtWins": 11,
      "regulationWinPctg": 0.384615,
      "regulationWins": 10,
      "roadGamesPlayed": 11,
      "roadGoalDifferential": 1,
      "roadGoalsAgainst": 29,
      "roadGoalsFor": 30,
      "roadLosses": 2,
      "roadOtLosses": 4,
      "roadPoints": 14,
      "roadRegulationPlusOtWins": 5,
      "roadRegulationWins": 4,
      "roadTies": 0,
      "roadWins": 5,
      "seasonId": 20252026,
      "shootoutLosses": 2,
      "shootoutWins": 1,
      "streakCode": "W",
      "streakCount": 2,
      "teamName": {
        "default": "Vegas Golden Knights",
        "fr": "Golden Knights de Vegas"
      },
      "teamCommonName": {
        "default": "Golden Knights"
      },
      "teamAbbrev": {
        "default": "VGK"
      },
      "teamLogo": "https://assets.nhle.com/logos/nhl/svg/VGK_light.svg",
      "ties": 0,
      "waiversSequence": 24,
      "wildcardSequence": 0,
      "winPctg": 0.461538,
      "wins": 12
    },
    {
      "conferenceAbbrev": "E",
      "conferenceHomeSequence": 16,
      "conferenceL10Sequence": 10,
      "conferenceName": "Eastern",
      "conferenceRoadSequence": 1,
      "conferenceSequence": 8,
      "date": "2025-12-04",
      "divisionAbbrev": "M",
      "divisionHomeSequence": 8,
      "divisionL10Sequence": 7,
      "divisionName": "Metropolitan",
      "divisionRoadSequence": 1,
      "divisionSequence": 7,
      "gameTypeId": 2,
      "gamesPlayed": 29,
      "goalDifferential": 4,
      "goalDifferentialPctg": 0.137931,
      "goalAgainst": 75,
      "goalFor": 79,
      "goalsForPctg": 2.724138,
      "homeGamesPlayed": 12,
      "homeGoalDifferential": -16,
      "homeGoalsAgainst": 36,
      "homeGoalsFor": 20,
      "homeLosses": 8,
      "homeOtLosses": 1,
      "homePoints": 7,
      "homeRegulationPlusOtWins": 3,
      "homeRegulationWins": 2,
      "homeTies": 0,
      "homeWins": 3,
      "l10GamesPlayed": 10,
      "l10GoalDifferential": 1,
      "l10GoalsAgainst": 28,
      "l10GoalsFor": 29,
      "l10Losses": 5,
      "l10OtLosses": 0,
      "l10Points": 10,
      "l10RegulationPlusOtWins": 5,
      "l10RegulationWins": 4,
      "l10Ties": 0,
      "l10Wins": 5,
      "leagueHomeSequence": 32,
      "leagueL10Sequence": 16,
      "leagueRoadSequence": 1,
      "leagueSequence": 13,
      "losses": 12,
      "otLosses": 2,
      "placeName": {
        "default": "NY Rangers"
      },
      "pointPctg": 0.551724,
      "points": 32,
      "regulationPlusOtWinPctg": 0.482759,
      "regulationPlusOtWins": 14,
      "regulationWinPctg": 0.37931,
      "regulationWins": 11,
      "roadGamesPlayed": 17,
      "roadGoalDifferential": 20,
      "roadGoalsAgainst": 39,
      "roadGoalsFor": 59,
      "roadLosses": 4,
      "roadOtLosses": 1,
      "roadPoints": 25,
      "roadRegulationPlusOtWins": 11,
      "roadRegulationWins": 9,
      "roadTies": 0,
      "roadWins": 12,
      "seasonId": 20252026,
      "shootoutLosses": 0,
      "shootoutWins": 1,
      "streakCode": "W",
      "streakCount": 2,
      "teamName": {
        "default": "New York Rangers",
        "fr": "Rangers de New York"
      },
      "teamCommonName": {
        "default": "Rangers"
      },
      "teamAbbrev": {
        "default": "NYR"
      },
      "teamLogo": "https://assets.nhle.com/logos/nhl/svg/NYR_light.svg",
      "ties": 0,
      "waiversSequence": 13,
      "wildcardSequence": 4,
      "winPctg": 0.517241,
      "wins": 15
    },
    {
      "conferenceAbbrev": "E",
      "conferenceHomeSequence": 1,
      "conferenceL10Sequence": 12,
      "conferenceName": "Eastern",
      "conferenceRoadSequence": 13,
      "conferenceSequence": 9,
      "date": "2025-12-04",
      "divisionAbbrev": "A",
      "divisionHomeSequence": 1,
      "divisionL10Sequence": 5,
      "divisionName": "Atlantic",
      "divisionRoadSequence": 5,
      "divisionSequence": 2,
      "gameTypeId": 2,
      "gamesPlayed": 29,
      "goalDifferential": -1,
      "goalDifferentialPctg": -0.034483,
      "goalAgainst": 93,
      "goalFor": 92,
      "goalsForPctg": 3.172414,
      "homeGamesPlayed": 15,
      "homeGoalDifferential": 6,
      "homeGoalsAgainst": 45,
      "homeGoalsFor": 51,
      "homeLosses": 5,
      "homeOtLosses": 0,
      "homePoints": 20,
      "homeRegulationPlusOtWins": 9,
      "homeRegulationWins": 6,
      "homeTies": 0,
      "homeWins": 10,
      "l10GamesPlayed": 10,
      "l10GoalDifferential": -2,
      "l10GoalsAgainst": 29,
      "l10GoalsFor": 27,
      "l10Losses": 5,
      "l10OtLosses": 0,
      "l10Points": 10,
      "l10RegulationPlusOtWins": 4,
      "l10RegulationWins": 3,
      "l10Ties": 0,
      "l10Wins": 5,
      "leagueHomeSequence": 3,
      "leagueL10Sequence": 20,
      "leagueRoadSequence": 25,
      "leagueSequence": 14,
      "losses": 13,
      "otLosses": 0,
      "placeName": {
        "default": "Boston"
      },
      "pointPctg": 0.551724,
      "points": 32,
      "regulationPlusOtWinPctg": 0.482759,
      "regulationPlusOtWins": 14,
      "regulationWinPctg": 0.344828,
      "regulationWins": 10,
      "roadGamesPlayed": 14,
      "roadGoalDifferential": -7,
      "roadGoalsAgainst": 48,
      "roadGoalsFor": 41,
      "roadLosses": 8,
      "roadOtLosses": 0,
      "roadPoints": 12,
      "roadRegulationPlusOtWins": 5,
      "roadRegulationWins": 4,
      "roadTies": 0,
      "roadWins": 6,
      "seasonId": 20252026,
      "shootoutLosses": 0,
      "shootoutWins": 2,
      "streakCode": "W",
      "streakCount": 1,
      "teamName": {
        "default": "Boston Bruins",
        "fr": "Bruins de Boston"
      },
      "teamCommonName": {
        "default": "Bruins"
      },
      "teamAbbrev": {
        "default": "BOS"
      },
      "teamLogo": "https://assets.nhle.com/logos/nhl/svg/BOS_light.svg?season=20252026",
      "ties": 0,
      "waiversSequence": 12,
      "wildcardSequence": 0,
      "winPctg": 0.551724,
      "wins": 16
    },
    {
      "conferenceAbbrev": "E",
      "conferenceHomeSequence": 13,
      "conferenceL10Sequence": 15,
      "conferenceName": "Eastern",
      "conferenceRoadSequence": 7,
      "conferenceSequence": 10,
      "date": "2025-12-04",
      "divisionAbbrev": "A",
      "divisionHomeSequence": 7,
      "divisionL10Sequence": 8,
      "divisionName": "Atlantic",
      "divisionRoadSequence": 2,
      "divisionSequence": 3,
      "gameTypeId": 2,
      "gamesPlayed": 26,
      "goalDifferential": -7,
      "goalDifferentialPctg": -0.269231,
      "goalAgainst": 94,
      "goalFor": 87,
      "goalsForPctg": 3.346154,
      "homeGamesPlayed": 14,
      "homeGoalDifferential": -8,
      "homeGoalsAgainst": 54,
      "homeGoalsFor": 46,
      "homeLosses": 6,
      "homeOtLosses": 1,
      "homePoints": 15,
      "homeRegulationPlusOtWins": 6,
      "homeRegulationWins": 3,
      "homeTies": 0,
      "homeWins": 7,
      "l10GamesPlayed": 10,
      "l10GoalDifferential": -13,
      "l10GoalsAgainst": 42,
      "l10GoalsFor": 29,
      "l10Losses": 5,
      "l10OtLosses": 1,
      "l10Points": 9,
      "l10RegulationPlusOtWins": 3,
      "l10RegulationWins": 3,
      "l10Ties": 0,
      "l10Wins": 4,
      "leagueHomeSequence": 22,
      "leagueL10Sequence": 27,
      "leagueRoadSequence": 10,
      "leagueSequence": 15,
      "losses": 9,
      "otLosses": 3,
      "placeName": {
        "default": "Montréal"
      },
      "pointPctg": 0.596154,
      "points": 31,
      "regulationPlusOtWinPctg": 0.5,
      "regulationPlusOtWins": 13,
      "regulationWinPctg": 0.307692,
      "regulationWins": 8,
      "roadGamesPlayed": 12,
      "roadGoalDifferential": 1,
      "roadGoalsAgainst": 40,
      "roadGoalsFor": 41,
      "roadLosses": 3,
      "roadOtLosses": 2,
      "roadPoints": 16,
      "roadRegulationPlusOtWins": 7,
      "roadRegulationWins": 5,
      "roadTies": 0,
      "roadWins": 7,
      "seasonId": 20252026,
      "shootoutLosses": 2,
      "shootoutWins": 1,
      "streakCode": "W",
      "streakCount": 1,
      "teamName": {
        "default": "Montréal Canadiens",
        "fr": "Canadiens de Montréal"
      },
      "teamCommonName": {
        "default": "Canadiens"
      },
      "teamAbbrev": {
        "default": "MTL"
      },
      "teamLogo": "https://assets.nhle.com/logos/nhl/svg/MTL_light.svg",
      "ties": 0,
      "waiversSequence": 21,
      "wildcardSequence": 0,
      "winPctg": 0.538462,
      "wins": 14
    },
    {
      "conferenceAbbrev": "W",
      "conferenceHomeSequence": 15,
      "conferenceL10Sequence": 6,
      "conferenceName": "Western",
      "conferenceRoadSequence": 2,
      "conferenceSequence": 6,
      "date": "2025-12-04",
      "divisionAbbrev": "P",
      "divisionHomeSequence": 7,
      "divisionL10Sequence": 3,
      "divisionName": "Pacific",
      "divisionRoadSequence": 1,
      "divisionSequence": 3,
      "gameTypeId": 2,
      "gamesPlayed": 27,
      "goalDifferential": -5,
      "goalDifferentialPctg": -0.185185,
      "goalAgainst": 75,
      "goalFor": 70,
      "goalsForPctg": 2.592593,
      "homeGamesPlayed": 12,
      "homeGoalDifferential": -12,
      "homeGoalsAgainst": 34,
      "homeGoalsFor": 22,
      "homeLosses": 6,
      "homeOtLosses": 3,
      "homePoints": 9,
      "homeRegulationPlusOtWins": 3,
      "homeRegulationWins": 2,
      "homeTies": 0,
      "homeWins": 3,
      "l10GamesPlayed": 10,
      "l10GoalDifferential": -3,
      "l10GoalsAgainst": 23,
      "l10GoalsFor": 20,
      "l10Losses": 3,
      "l10OtLosses": 3,
      "l10Points": 11,
      "l10RegulationPlusOtWins": 4,
      "l10RegulationWins": 2,
      "l10Ties": 0,
      "l10Wins": 4,
      "leagueHomeSequence": 30,
      "leagueL10Sequence": 15,
      "leagueRoadSequence": 3,
      "leagueSequence": 16,
      "losses": 8,
      "otLosses": 7,
      "placeName": {
        "default": "Los Angeles"
      },
      "pointPctg": 0.574074,
      "points": 31,
      "regulationPlusOtWinPctg": 0.407407,
      "regulationPlusOtWins": 11,
      "regulationWinPctg": 0.259259,
      "regulationWins": 7,
      "roadGamesPlayed": 15,
      "roadGoalDifferential": 7,
      "roadGoalsAgainst": 41,
      "roadGoalsFor": 48,
      "roadLosses": 2,
      "roadOtLosses": 4,
      "roadPoints": 22,
      "roadRegulationPlusOtWins": 8,
      "roadRegulationWins": 5,
      "roadTies": 0,
      "roadWins": 9,
      "seasonId": 20252026,
      "shootoutLosses": 5,
      "shootoutWins": 1,
      "streakCode": "L",
      "streakCount": 2,
      "teamName": {
        "default": "Los Angeles Kings",
        "fr": "Kings de Los Angeles"
      },
      "teamCommonName": {
        "default": "Kings"
      },
      "teamAbbrev": {
        "default": "LAK"
      },
      "teamLogo": "https://assets.nhle.com/logos/nhl/svg/LAK_light.svg",
      "ties": 0,
      "waiversSequence": 19,
      "wildcardSequence": 0,
      "winPctg": 0.444444,
      "wins": 12
    },
    {
      "conferenceAbbrev": "E",
      "conferenceHomeSequence": 12,
      "conferenceL10Sequence": 8,
      "conferenceName": "Eastern",
      "conferenceRoadSequence": 9,
      "conferenceSequence": 11,
      "date": "2025-12-04",
      "divisionAbbrev": "M",
      "divisionHomeSequence": 6,
      "divisionL10Sequence": 5,
      "divisionName": "Metropolitan",
      "divisionRoadSequence": 6,
      "divisionSequence": 8,
      "gameTypeId": 2,
      "gamesPlayed": 27,
      "goalDifferential": -6,
      "goalDifferentialPctg": -0.222222,
      "goalAgainst": 90,
      "goalFor": 84,
      "goalsForPctg": 3.111111,
      "homeGamesPlayed": 12,
      "homeGoalDifferential": -3,
      "homeGoalsAgainst": 39,
      "homeGoalsFor": 36,
      "homeLosses": 3,
      "homeOtLosses": 3,
      "homePoints": 15,
      "homeRegulationPlusOtWins": 4,
      "homeRegulationWins": 4,
      "homeTies": 0,
      "homeWins": 6,
      "l10GamesPlayed": 10,
      "l10GoalDifferential": -6,
      "l10GoalsAgainst": 35,
      "l10GoalsFor": 29,
      "l10Losses": 2,
      "l10OtLosses": 4,
      "l10Points": 12,
      "l10RegulationPlusOtWins": 2,
      "l10RegulationWins": 1,
      "l10Ties": 0,
      "l10Wins": 4,
      "leagueHomeSequence": 20,
      "leagueL10Sequence": 13,
      "leagueRoadSequence": 12,
      "leagueSequence": 17,
      "losses": 9,
      "otLosses": 5,
      "placeName": {
        "default": "Columbus"
      },
      "pointPctg": 0.574074,
      "points": 31,
      "regulationPlusOtWinPctg": 0.333333,
      "regulationPlusOtWins": 9,
      "regulationWinPctg": 0.259259,
      "regulationWins": 7,
      "roadGamesPlayed": 15,
      "roadGoalDifferential": -3,
      "roadGoalsAgainst": 51,
      "roadGoalsFor": 48,
      "roadLosses": 6,
      "roadOtLosses": 2,
      "roadPoints": 16,
      "roadRegulationPlusOtWins": 5,
      "roadRegulationWins": 3,
      "roadTies": 0,
      "roadWins": 7,
      "seasonId": 20252026,
      "shootoutLosses": 1,
      "shootoutWins": 4,
      "streakCode": "W",
      "streakCount": 2,
      "teamName": {
        "default": "Columbus Blue Jackets",
        "fr": "Blue Jackets de Columbus"
      },
      "teamCommonName": {
        "default": "Blue Jackets"
      },
      "teamAbbrev": {
        "default": "CBJ"
      },
      "teamLogo": "https://assets.nhle.com/logos/nhl/svg/CBJ_light.svg",
      "ties": 0,
      "waiversSequence": 18,
      "wildcardSequence": 5,
      "winPctg": 0.481481,
      "wins": 13
    },
    {
      "conferenceAbbrev": "E",
      "conferenceHomeSequence": 7,
      "conferenceL10Sequence": 13,
      "conferenceName": "Eastern",
      "conferenceRoadSequence": 12,
      "conferenceSequence": 12,
      "date": "2025-12-04",
      "divisionAbbrev": "A",
      "divisionHomeSequence": 4,
      "divisionL10Sequence": 6,
      "divisionName": "Atlantic",
      "divisionRoadSequence": 4,
      "divisionSequence": 4,
      "gameTypeId": 2,
      "gamesPlayed": 28,
      "goalDifferential": -12,
      "goalDifferentialPctg": -0.428571,
      "goalAgainst": 99,
      "goalFor": 87,
      "goalsForPctg": 3.107143,
      "homeGamesPlayed": 16,
      "homeGoalDifferential": -5,
      "homeGoalsAgainst": 59,
      "homeGoalsFor": 54,
      "homeLosses": 6,
      "homeOtLosses": 1,
      "homePoints": 19,
      "homeRegulationPlusOtWins": 9,
      "homeRegulationWins": 7,
      "homeTies": 0,
      "homeWins": 9,
      "l10GamesPlayed": 10,
      "l10GoalDifferential": -9,
      "l10GoalsAgainst": 40,
      "l10GoalsFor": 31,
      "l10Losses": 4,
      "l10OtLosses": 2,
      "l10Points": 10,
      "l10RegulationPlusOtWins": 4,
      "l10RegulationWins": 3,
      "l10Ties": 0,
      "l10Wins": 4,
      "leagueHomeSequence": 10,
      "leagueL10Sequence": 23,
      "leagueRoadSequence": 24,
      "leagueSequence": 18,
      "losses": 11,
      "otLosses": 3,
      "placeName": {
        "default": "Detroit"
      },
      "pointPctg": 0.553571,
      "points": 31,
      "regulationPlusOtWinPctg": 0.428571,
      "regulationPlusOtWins": 12,
      "regulationWinPctg": 0.357143,
      "regulationWins": 10,
      "roadGamesPlayed": 12,
      "roadGoalDifferential": -7,
      "roadGoalsAgainst": 40,
      "roadGoalsFor": 33,
      "roadLosses": 5,
      "roadOtLosses": 2,
      "roadPoints": 12,
      "roadRegulationPlusOtWins": 3,
      "roadRegulationWins": 3,
      "roadTies": 0,
      "roadWins": 5,
      "seasonId": 20252026,
      "shootoutLosses": 2,
      "shootoutWins": 2,
      "streakCode": "OT",
      "streakCount": 1,
      "teamName": {
        "default": "Detroit Red Wings",
        "fr": "Red Wings de Detroit"
      },
      "teamCommonName": {
        "default": "Red Wings"
      },
      "teamAbbrev": {
        "default": "DET"
      },
      "teamLogo": "https://assets.nhle.com/logos/nhl/svg/DET_light.svg?season=20252026",
      "ties": 0,
      "waiversSequence": 14,
      "wildcardSequence": 6,
      "winPctg": 0.5,
      "wins": 14
    },
    {
      "conferenceAbbrev": "W",
      "conferenceHomeSequence": 9,
      "conferenceL10Sequence": 7,
      "conferenceName": "Western",
      "conferenceRoadSequence": 6,
      "conferenceSequence": 7,
      "date": "2025-12-04",
      "divisionAbbrev": "C",
      "divisionHomeSequence": 5,
      "divisionL10Sequence": 4,
      "divisionName": "Central",
      "divisionRoadSequence": 4,
      "divisionSequence": 4,
      "gameTypeId": 2,
      "gamesPlayed": 27,
      "goalDifferential": 7,
      "goalDifferentialPctg": 0.259259,
      "goalAgainst": 78,
      "goalFor": 85,
      "goalsForPctg": 3.148148,
      "homeGamesPlayed": 14,
      "homeGoalDifferential": 4,
      "homeGoalsAgainst": 37,
      "homeGoalsFor": 41,
      "homeLosses": 5,
      "homeOtLosses": 3,
      "homePoints": 15,
      "homeRegulationPlusOtWins": 6,
      "homeRegulationWins": 5,
      "homeTies": 0,
      "homeWins": 6,
      "l10GamesPlayed": 10,
      "l10GoalDifferential": -4,
      "l10GoalsAgainst": 33,
      "l10GoalsFor": 29,
      "l10Losses": 4,
      "l10OtLosses": 2,
      "l10Points": 10,
      "l10RegulationPlusOtWins": 4,
      "l10RegulationWins": 4,
      "l10Ties": 0,
      "l10Wins": 4,
      "leagueHomeSequence": 21,
      "leagueL10Sequence": 18,
      "leagueRoadSequence": 15,
      "leagueSequence": 19,
      "losses": 9,
      "otLosses": 6,
      "placeName": {
        "default": "Chicago"
      },
      "pointPctg": 0.555556,
      "points": 30,
      "regulationPlusOtWinPctg": 0.444444,
      "regulationPlusOtWins": 12,
      "regulationWinPctg": 0.407407,
      "regulationWins": 11,
      "roadGamesPlayed": 13,
      "roadGoalDifferential": 3,
      "roadGoalsAgainst": 41,
      "roadGoalsFor": 44,
      "roadLosses": 4,
      "roadOtLosses": 3,
      "roadPoints": 15,
      "roadRegulationPlusOtWins": 6,
      "roadRegulationWins": 6,
      "roadTies": 0,
      "roadWins": 6,
      "seasonId": 20252026,
      "shootoutLosses": 2,
      "shootoutWins": 0,
      "streakCode": "W",
      "streakCount": 1,
      "teamName": {
        "default": "Chicago Blackhawks",
        "fr": "Blackhawks de Chicago"
      },
      "teamCommonName": {
        "default": "Blackhawks"
      },
      "teamAbbrev": {
        "default": "CHI"
      },
      "teamLogo": "https://assets.nhle.com/logos/nhl/svg/CHI_light.svg?season=20252026",
      "ties": 0,
      "waiversSequence": 16,
      "wildcardSequence": 1,
      "winPctg": 0.444444,
      "wins": 12
    },
    {
      "conferenceAbbrev": "E",
      "conferenceHomeSequence": 15,
      "conferenceL10Sequence": 11,
      "conferenceName": "Eastern",
      "conferenceRoadSequence": 8,
      "conferenceSequence": 13,
      "date": "2025-12-04",
      "divisionAbbrev": "A",
      "divisionHomeSequence": 8,
      "divisionL10Sequence": 4,
      "divisionName": "Atlantic",
      "divisionRoadSequence": 3,
      "divisionSequence": 5,
      "gameTypeId": 2,
      "gamesPlayed": 27,
      "goalDifferential": -4,
      "goalDifferentialPctg": -0.148148,
      "goalAgainst": 90,
      "goalFor": 86,
      "goalsForPctg": 3.185185,
      "homeGamesPlayed": 12,
      "homeGoalDifferential": 3,
      "homeGoalsAgainst": 34,
      "homeGoalsFor": 37,
      "homeLosses": 4,
      "homeOtLosses": 2,
      "homePoints": 14,
      "homeRegulationPlusOtWins": 4,
      "homeRegulationWins": 4,
      "homeTies": 0,
      "homeWins": 6,
      "l10GamesPlayed": 10,
      "l10GoalDifferential": -2,
      "l10GoalsAgainst": 29,
      "l10GoalsFor": 27,
      "l10Losses": 5,
      "l10OtLosses": 0,
      "l10Points": 10,
      "l10RegulationPlusOtWins": 4,
      "l10RegulationWins": 4,
      "l10Ties": 0,
      "l10Wins": 5,
      "leagueHomeSequence": 25,
      "leagueL10Sequence": 17,
      "leagueRoadSequence": 11,
      "leagueSequence": 20,
      "losses": 10,
      "otLosses": 4,
      "placeName": {
        "default": "Ottawa"
      },
      "pointPctg": 0.555556,
      "points": 30,
      "regulationPlusOtWinPctg": 0.37037,
      "regulationPlusOtWins": 10,
      "regulationWinPctg": 0.333333,
      "regulationWins": 9,
      "roadGamesPlayed": 15,
      "roadGoalDifferential": -7,
      "roadGoalsAgainst": 56,
      "roadGoalsFor": 49,
      "roadLosses": 6,
      "roadOtLosses": 2,
      "roadPoints": 16,
      "roadRegulationPlusOtWins": 6,
      "roadRegulationWins": 5,
      "roadTies": 0,
      "roadWins": 7,
      "seasonId": 20252026,
      "shootoutLosses": 0,
      "shootoutWins": 3,
      "streakCode": "L",
      "streakCount": 1,
      "teamName": {
        "default": "Ottawa Senators",
        "fr": "Sénateurs d'Ottawa"
      },
      "teamCommonName": {
        "default": "Senators",
        "fr": "Sénateurs"
      },
      "teamAbbrev": {
        "default": "OTT"
      },
      "teamLogo": "https://assets.nhle.com/logos/nhl/svg/OTT_light.svg",
      "ties": 0,
      "waiversSequence": 15,
      "wildcardSequence": 7,
      "winPctg": 0.481481,
      "wins": 13
    },
    {
      "conferenceAbbrev": "E",
      "conferenceHomeSequence": 6,
      "conferenceL10Sequence": 6,
      "conferenceName": "Eastern",
      "conferenceRoadSequence": 14,
      "conferenceSequence": 14,
      "date": "2025-12-04",
      "divisionAbbrev": "A",
      "divisionHomeSequence": 3,
      "divisionL10Sequence": 3,
      "divisionName": "Atlantic",
      "divisionRoadSequence": 6,
      "divisionSequence": 6,
      "gameTypeId": 2,
      "gamesPlayed": 27,
      "goalDifferential": 3,
      "goalDifferentialPctg": 0.111111,
      "goalAgainst": 91,
      "goalFor": 94,
      "goalsForPctg": 3.481481,
      "homeGamesPlayed": 15,
      "homeGoalDifferential": 3,
      "homeGoalsAgainst": 50,
      "homeGoalsFor": 53,
      "homeLosses": 4,
      "homeOtLosses": 3,
      "homePoints": 19,
      "homeRegulationPlusOtWins": 8,
      "homeRegulationWins": 5,
      "homeTies": 0,
      "homeWins": 8,
      "l10GamesPlayed": 10,
      "l10GoalDifferential": 6,
      "l10GoalsAgainst": 26,
      "l10GoalsFor": 32,
      "l10Losses": 3,
      "l10OtLosses": 2,
      "l10Points": 12,
      "l10RegulationPlusOtWins": 5,
      "l10RegulationWins": 3,
      "l10Ties": 0,
      "l10Wins": 5,
      "leagueHomeSequence": 9,
      "leagueL10Sequence": 11,
      "leagueRoadSequence": 29,
      "leagueSequence": 21,
      "losses": 11,
      "otLosses": 3,
      "placeName": {
        "default": "Toronto"
      },
      "pointPctg": 0.537037,
      "points": 29,
      "regulationPlusOtWinPctg": 0.481481,
      "regulationPlusOtWins": 13,
      "regulationWinPctg": 0.333333,
      "regulationWins": 9,
      "roadGamesPlayed": 12,
      "roadGoalDifferential": 0,
      "roadGoalsAgainst": 41,
      "roadGoalsFor": 41,
      "roadLosses": 7,
      "roadOtLosses": 0,
      "roadPoints": 10,
      "roadRegulationPlusOtWins": 5,
      "roadRegulationWins": 4,
      "roadTies": 0,
      "roadWins": 5,
      "seasonId": 20252026,
      "shootoutLosses": 0,
      "shootoutWins": 0,
      "streakCode": "W",
      "streakCount": 3,
      "teamName": {
        "default": "Toronto Maple Leafs",
        "fr": "Maple Leafs de Toronto"
      },
      "teamCommonName": {
        "default": "Maple Leafs"
      },
      "teamAbbrev": {
        "default": "TOR"
      },
      "teamLogo": "https://assets.nhle.com/logos/nhl/svg/TOR_light.svg",
      "ties": 0,
      "waiversSequence": 11,
      "wildcardSequence": 8,
      "winPctg": 0.481481,
      "wins": 13
    },
    {
      "conferenceAbbrev": "W",
      "conferenceHomeSequence": 7,
      "conferenceL10Sequence": 14,
      "conferenceName": "Western",
      "conferenceRoadSequence": 11,
      "conferenceSequence": 8,
      "date": "2025-12-04",
      "divisionAbbrev": "C",
      "divisionHomeSequence": 4,
      "divisionL10Sequence": 7,
      "divisionName": "Central",
      "divisionRoadSequence": 6,
      "divisionSequence": 5,
      "gameTypeId": 2,
      "gamesPlayed": 28,
      "goalDifferential": 4,
      "goalDifferentialPctg": 0.142857,
      "goalAgainst": 83,
      "goalFor": 87,
      "goalsForPctg": 3.107143,
      "homeGamesPlayed": 11,
      "homeGoalDifferential": 8,
      "homeGoalsAgainst": 29,
      "homeGoalsFor": 37,
      "homeLosses": 3,
      "homeOtLosses": 1,
      "homePoints": 15,
      "homeRegulationPlusOtWins": 7,
      "homeRegulationWins": 6,
      "homeTies": 0,
      "homeWins": 7,
      "l10GamesPlayed": 10,
      "l10GoalDifferential": 1,
      "l10GoalsAgainst": 28,
      "l10GoalsFor": 29,
      "l10Losses": 5,
      "l10OtLosses": 2,
      "l10Points": 8,
      "l10RegulationPlusOtWins": 3,
      "l10RegulationWins": 3,
      "l10Ties": 0,
      "l10Wins": 3,
      "leagueHomeSequence": 18,
      "leagueL10Sequence": 29,
      "leagueRoadSequence": 21,
      "leagueSequence": 22,
      "losses": 12,
      "otLosses": 3,
      "placeName": {
        "default": "Utah"
      },
      "pointPctg": 0.517857,
      "points": 29,
      "regulationPlusOtWinPctg": 0.464286,
      "regulationPlusOtWins": 13,
      "regulationWinPctg": 0.357143,
      "regulationWins": 10,
      "roadGamesPlayed": 17,
      "roadGoalDifferential": -4,
      "roadGoalsAgainst": 54,
      "roadGoalsFor": 50,
      "roadLosses": 9,
      "roadOtLosses": 2,
      "roadPoints": 14,
      "roadRegulationPlusOtWins": 6,
      "roadRegulationWins": 4,
      "roadTies": 0,
      "roadWins": 6,
      "seasonId": 20252026,
      "shootoutLosses": 0,
      "shootoutWins": 0,
      "streakCode": "W",
      "streakCount": 1,
      "teamName": {
        "default": "Utah Mammoth",
        "fr": "Mammoth de l'Utah"
      },
      "teamCommonName": {
        "default": "Mammoth"
      },
      "teamAbbrev": {
        "default": "UTA"
      },
      "teamLogo": "https://assets.nhle.com/logos/nhl/svg/UTA_light.svg?season=20252026",
      "ties": 0,
      "waiversSequence": 9,
      "wildcardSequence": 2,
      "winPctg": 0.464286,
      "wins": 13
    },
    {
      "conferenceAbbrev": "W",
      "conferenceHomeSequence": 2,
      "conferenceL10Sequence": 9,
      "conferenceName": "Western",
      "conferenceRoadSequence": 16,
      "conferenceSequence": 9,
      "date": "2025-12-04",
      "divisionAbbrev": "P",
      "divisionHomeSequence": 1,
      "divisionL10Sequence": 4,
      "divisionName": "Pacific",
      "divisionRoadSequence": 8,
      "divisionSequence": 4,
      "gameTypeId": 2,
      "gamesPlayed": 28,
      "goalDifferential": -13,
      "goalDifferentialPctg": -0.464286,
      "goalAgainst": 94,
      "goalFor": 81,
      "goalsForPctg": 2.892857,
      "homeGamesPlayed": 17,
      "homeGoalDifferential": -3,
      "homeGoalsAgainst": 53,
      "homeGoalsFor": 50,
      "homeLosses": 5,
      "homeOtLosses": 3,
      "homePoints": 21,
      "homeRegulationPlusOtWins": 8,
      "homeRegulationWins": 6,
      "homeTies": 0,
      "homeWins": 9,
      "l10GamesPlayed": 10,
      "l10GoalDifferential": -9,
      "l10GoalsAgainst": 35,
      "l10GoalsFor": 26,
      "l10Losses": 5,
      "l10OtLosses": 0,
      "l10Points": 10,
      "l10RegulationPlusOtWins": 4,
      "l10RegulationWins": 3,
      "l10Ties": 0,
      "l10Wins": 5,
      "leagueHomeSequence": 2,
      "leagueL10Sequence": 21,
      "leagueRoadSequence": 31,
      "leagueSequence": 23,
      "losses": 12,
      "otLosses": 3,
      "placeName": {
        "default": "San Jose"
      },
      "pointPctg": 0.517857,
      "points": 29,
      "regulationPlusOtWinPctg": 0.428571,
      "regulationPlusOtWins": 12,
      "regulationWinPctg": 0.25,
      "regulationWins": 7,
      "roadGamesPlayed": 11,
      "roadGoalDifferential": -10,
      "roadGoalsAgainst": 41,
      "roadGoalsFor": 31,
      "roadLosses": 7,
      "roadOtLosses": 0,
      "roadPoints": 8,
      "roadRegulationPlusOtWins": 4,
      "roadRegulationWins": 1,
      "roadTies": 0,
      "roadWins": 4,
      "seasonId": 20252026,
      "shootoutLosses": 1,
      "shootoutWins": 1,
      "streakCode": "L",
      "streakCount": 1,
      "teamName": {
        "default": "San Jose Sharks",
        "fr": "Sharks de San Jose"
      },
      "teamCommonName": {
        "default": "Sharks"
      },
      "teamAbbrev": {
        "default": "SJS"
      },
      "teamLogo": "https://assets.nhle.com/logos/nhl/svg/SJS_light.svg",
      "ties": 0,
      "waiversSequence": 8,
      "wildcardSequence": 3,
      "winPctg": 0.464286,
      "wins": 13
    },
    {
      "conferenceAbbrev": "W",
      "conferenceHomeSequence": 10,
      "conferenceL10Sequence": 12,
      "conferenceName": "Western",
      "conferenceRoadSequence": 9,
      "conferenceSequence": 10,
      "date": "2025-12-04",
      "divisionAbbrev": "P",
      "divisionHomeSequence": 5,
      "divisionL10Sequence": 7,
      "divisionName": "Pacific",
      "divisionRoadSequence": 4,
      "divisionSequence": 5,
      "gameTypeId": 2,
      "gamesPlayed": 28,
      "goalDifferential": -10,
      "goalDifferentialPctg": -0.357143,
      "goalAgainst": 100,
      "goalFor": 90,
      "goalsForPctg": 3.214286,
      "homeGamesPlayed": 11,
      "homeGoalDifferential": -3,
      "homeGoalsAgainst": 45,
      "homeGoalsFor": 42,
      "homeLosses": 3,
      "homeOtLosses": 2,
      "homePoints": 14,
      "homeRegulationPlusOtWins": 6,
      "homeRegulationWins": 4,
      "homeTies": 0,
      "homeWins": 6,
      "l10GamesPlayed": 10,
      "l10GoalDifferential": -2,
      "l10GoalsAgainst": 38,
      "l10GoalsFor": 36,
      "l10Losses": 5,
      "l10OtLosses": 1,
      "l10Points": 9,
      "l10RegulationPlusOtWins": 4,
      "l10RegulationWins": 3,
      "l10Ties": 0,
      "l10Wins": 4,
      "leagueHomeSequence": 23,
      "leagueL10Sequence": 26,
      "leagueRoadSequence": 18,
      "leagueSequence": 24,
      "losses": 11,
      "otLosses": 5,
      "placeName": {
        "default": "Edmonton"
      },
      "pointPctg": 0.517857,
      "points": 29,
      "regulationPlusOtWinPctg": 0.428571,
      "regulationPlusOtWins": 12,
      "regulationWinPctg": 0.25,
      "regulationWins": 7,
      "roadGamesPlayed": 17,
      "roadGoalDifferential": -7,
      "roadGoalsAgainst": 55,
      "roadGoalsFor": 48,
      "roadLosses": 8,
      "roadOtLosses": 3,
      "roadPoints": 15,
      "roadRegulationPlusOtWins": 6,
      "roadRegulationWins": 3,
      "roadTies": 0,
      "roadWins": 6,
      "seasonId": 20252026,
      "shootoutLosses": 2,
      "shootoutWins": 0,
      "streakCode": "W",
      "streakCount": 1,
      "teamName": {
        "default": "Edmonton Oilers",
        "fr": "Oilers d'Edmonton"
      },
      "teamCommonName": {
        "default": "Oilers"
      },
      "teamAbbrev": {
        "default": "EDM"
      },
      "teamLogo": "https://assets.nhle.com/logos/nhl/svg/EDM_light.svg",
      "ties": 0,
      "waiversSequence": 7,
      "wildcardSequence": 4,
      "winPctg": 0.428571,
      "wins": 12
    },
    {
      "conferenceAbbrev": "W",
      "conferenceHomeSequence": 8,
      "conferenceL10Sequence": 10,
      "conferenceName": "Western",
      "conferenceRoadSequence": 12,
      "conferenceSequence": 11,
      "date": "2025-12-04",
      "divisionAbbrev": "P",
      "divisionHomeSequence": 4,
      "divisionL10Sequence": 5,
      "divisionName": "Pacific",
      "divisionRoadSequence": 6,
      "divisionSequence": 6,
      "gameTypeId": 2,
      "gamesPlayed": 25,
      "goalDifferential": -12,
      "goalDifferentialPctg": -0.48,
      "goalAgainst": 75,
      "goalFor": 63,
      "goalsForPctg": 2.52,
      "homeGamesPlayed": 12,
      "homeGoalDifferential": -2,
      "homeGoalsAgainst": 31,
      "homeGoalsFor": 29,
      "homeLosses": 3,
      "homeOtLosses": 3,
      "homePoints": 15,
      "homeRegulationPlusOtWins": 6,
      "homeRegulationWins": 5,
      "homeTies": 0,
      "homeWins": 6,
      "l10GamesPlayed": 10,
      "l10GoalDifferential": -7,
      "l10GoalsAgainst": 31,
      "l10GoalsFor": 24,
      "l10Losses": 4,
      "l10OtLosses": 2,
      "l10Points": 10,
      "l10RegulationPlusOtWins": 4,
      "l10RegulationWins": 3,
      "l10Ties": 0,
      "l10Wins": 4,
      "leagueHomeSequence": 19,
      "leagueL10Sequence": 22,
      "leagueRoadSequence": 23,
      "leagueSequence": 25,
      "losses": 8,
      "otLosses": 6,
      "placeName": {
        "default": "Seattle"
      },
      "pointPctg": 0.56,
      "points": 28,
      "regulationPlusOtWinPctg": 0.44,
      "regulationPlusOtWins": 11,
      "regulationWinPctg": 0.28,
      "regulationWins": 7,
      "roadGamesPlayed": 13,
      "roadGoalDifferential": -10,
      "roadGoalsAgainst": 44,
      "roadGoalsFor": 34,
      "roadLosses": 5,
      "roadOtLosses": 3,
      "roadPoints": 13,
      "roadRegulationPlusOtWins": 5,
      "roadRegulationWins": 2,
      "roadTies": 0,
      "roadWins": 5,
      "seasonId": 20252026,
      "shootoutLosses": 3,
      "shootoutWins": 0,
      "streakCode": "L",
      "streakCount": 3,
      "teamName": {
        "default": "Seattle Kraken",
        "fr": "Kraken de Seattle"
      },
      "teamCommonName": {
        "default": "Kraken"
      },
      "teamAbbrev": {
        "default": "SEA"
      },
      "teamLogo": "https://assets.nhle.com/logos/nhl/svg/SEA_light.svg",
      "ties": 0,
      "waiversSequence": 17,
      "wildcardSequence": 5,
      "winPctg": 0.44,
      "wins": 11
    },
    {
      "conferenceAbbrev": "W",
      "conferenceHomeSequence": 13,
      "conferenceL10Sequence": 15,
      "conferenceName": "Western",
      "conferenceRoadSequence": 8,
      "conferenceSequence": 12,
      "date": "2025-12-04",
      "divisionAbbrev": "C",
      "divisionHomeSequence": 8,
      "divisionL10Sequence": 8,
      "divisionName": "Central",
      "divisionRoadSequence": 5,
      "divisionSequence": 6,
      "gameTypeId": 2,
      "gamesPlayed": 26,
      "goalDifferential": 1,
      "goalDifferentialPctg": 0.038462,
      "goalAgainst": 78,
      "goalFor": 79,
      "goalsForPctg": 3.038462,
      "homeGamesPlayed": 11,
      "homeGoalDifferential": 6,
      "homeGoalsAgainst": 31,
      "homeGoalsFor": 37,
      "homeLosses": 5,
      "homeOtLosses": 0,
      "homePoints": 12,
      "homeRegulationPlusOtWins": 6,
      "homeRegulationWins": 6,
      "homeTies": 0,
      "homeWins": 6,
      "l10GamesPlayed": 10,
      "l10GoalDifferential": -9,
      "l10GoalsAgainst": 36,
      "l10GoalsFor": 27,
      "l10Losses": 6,
      "l10OtLosses": 1,
      "l10Points": 7,
      "l10RegulationPlusOtWins": 2,
      "l10RegulationWins": 2,
      "l10Ties": 0,
      "l10Wins": 3,
      "leagueHomeSequence": 28,
      "leagueL10Sequence": 31,
      "leagueRoadSequence": 17,
      "leagueSequence": 26,
      "losses": 12,
      "otLosses": 1,
      "placeName": {
        "default": "Winnipeg"
      },
      "pointPctg": 0.519231,
      "points": 27,
      "regulationPlusOtWinPctg": 0.461538,
      "regulationPlusOtWins": 12,
      "regulationWinPctg": 0.423077,
      "regulationWins": 11,
      "roadGamesPlayed": 15,
      "roadGoalDifferential": -5,
      "roadGoalsAgainst": 47,
      "roadGoalsFor": 42,
      "roadLosses": 7,
      "roadOtLosses": 1,
      "roadPoints": 15,
      "roadRegulationPlusOtWins": 6,
      "roadRegulationWins": 5,
      "roadTies": 0,
      "roadWins": 7,
      "seasonId": 20252026,
      "shootoutLosses": 1,
      "shootoutWins": 1,
      "streakCode": "OT",
      "streakCount": 1,
      "teamName": {
        "default": "Winnipeg Jets",
        "fr": "Jets de Winnipeg"
      },
      "teamCommonName": {
        "default": "Jets"
      },
      "teamAbbrev": {
        "default": "WPG"
      },
      "teamLogo": "https://assets.nhle.com/logos/nhl/svg/WPG_light.svg",
      "ties": 0,
      "waiversSequence": 10,
      "wildcardSequence": 6,
      "winPctg": 0.5,
      "wins": 13
    },
    {
      "conferenceAbbrev": "E",
      "conferenceHomeSequence": 8,
      "conferenceL10Sequence": 14,
      "conferenceName": "Eastern",
      "conferenceRoadSequence": 15,
      "conferenceSequence": 15,
      "date": "2025-12-04",
      "divisionAbbrev": "A",
      "divisionHomeSequence": 5,
      "divisionL10Sequence": 7,
      "divisionName": "Atlantic",
      "divisionRoadSequence": 7,
      "divisionSequence": 7,
      "gameTypeId": 2,
      "gamesPlayed": 26,
      "goalDifferential": -6,
      "goalDifferentialPctg": -0.230769,
      "goalAgainst": 83,
      "goalFor": 77,
      "goalsForPctg": 2.961538,
      "homeGamesPlayed": 16,
      "homeGoalDifferential": 1,
      "homeGoalsAgainst": 48,
      "homeGoalsFor": 49,
      "homeLosses": 6,
      "homeOtLosses": 2,
      "homePoints": 18,
      "homeRegulationPlusOtWins": 7,
      "homeRegulationWins": 7,
      "homeTies": 0,
      "homeWins": 8,
      "l10GamesPlayed": 10,
      "l10GoalDifferential": -1,
      "l10GoalsAgainst": 35,
      "l10GoalsFor": 34,
      "l10Losses": 5,
      "l10OtLosses": 1,
      "l10Points": 9,
      "l10RegulationPlusOtWins": 4,
      "l10RegulationWins": 4,
      "l10Ties": 0,
      "l10Wins": 4,
      "leagueHomeSequence": 13,
      "leagueL10Sequence": 25,
      "leagueRoadSequence": 30,
      "leagueSequence": 27,
      "losses": 12,
      "otLosses": 2,
      "placeName": {
        "default": "Florida",
        "fr": "Floride"
      },
      "pointPctg": 0.5,
      "points": 26,
      "regulationPlusOtWinPctg": 0.423077,
      "regulationPlusOtWins": 11,
      "regulationWinPctg": 0.423077,
      "regulationWins": 11,
      "roadGamesPlayed": 10,
      "roadGoalDifferential": -7,
      "roadGoalsAgainst": 35,
      "roadGoalsFor": 28,
      "roadLosses": 6,
      "roadOtLosses": 0,
      "roadPoints": 8,
      "roadRegulationPlusOtWins": 4,
      "roadRegulationWins": 4,
      "roadTies": 0,
      "roadWins": 4,
      "seasonId": 20252026,
      "shootoutLosses": 1,
      "shootoutWins": 1,
      "streakCode": "OT",
      "streakCount": 1,
      "teamName": {
        "default": "Florida Panthers",
        "fr": "Panthers de la Floride"
      },
      "teamCommonName": {
        "default": "Panthers"
      },
      "teamAbbrev": {
        "default": "FLA"
      },
      "teamLogo": "https://assets.nhle.com/logos/nhl/svg/FLA_light.svg",
      "ties": 0,
      "waiversSequence": 6,
      "wildcardSequence": 9,
      "winPctg": 0.461538,
      "wins": 12
    },
    {
      "conferenceAbbrev": "E",
      "conferenceHomeSequence": 3,
      "conferenceL10Sequence": 4,
      "conferenceName": "Eastern",
      "conferenceRoadSequence": 16,
      "conferenceSequence": 16,
      "date": "2025-12-04",
      "divisionAbbrev": "A",
      "divisionHomeSequence": 2,
      "divisionL10Sequence": 2,
      "divisionName": "Atlantic",
      "divisionRoadSequence": 8,
      "divisionSequence": 8,
      "gameTypeId": 2,
      "gamesPlayed": 27,
      "goalDifferential": -9,
      "goalDifferentialPctg": -0.333333,
      "goalAgainst": 92,
      "goalFor": 83,
      "goalsForPctg": 3.074074,
      "homeGamesPlayed": 16,
      "homeGoalDifferential": 9,
      "homeGoalsAgainst": 45,
      "homeGoalsFor": 54,
      "homeLosses": 5,
      "homeOtLosses": 2,
      "homePoints": 20,
      "homeRegulationPlusOtWins": 8,
      "homeRegulationWins": 8,
      "homeTies": 0,
      "homeWins": 9,
      "l10GamesPlayed": 10,
      "l10GoalDifferential": 5,
      "l10GoalsAgainst": 32,
      "l10GoalsFor": 37,
      "l10Losses": 4,
      "l10OtLosses": 0,
      "l10Points": 12,
      "l10RegulationPlusOtWins": 5,
      "l10RegulationWins": 4,
      "l10Ties": 0,
      "l10Wins": 6,
      "leagueHomeSequence": 6,
      "leagueL10Sequence": 8,
      "leagueRoadSequence": 32,
      "leagueSequence": 28,
      "losses": 12,
      "otLosses": 4,
      "placeName": {
        "default": "Buffalo"
      },
      "pointPctg": 0.481481,
      "points": 26,
      "regulationPlusOtWinPctg": 0.333333,
      "regulationPlusOtWins": 9,
      "regulationWinPctg": 0.296296,
      "regulationWins": 8,
      "roadGamesPlayed": 11,
      "roadGoalDifferential": -18,
      "roadGoalsAgainst": 47,
      "roadGoalsFor": 29,
      "roadLosses": 7,
      "roadOtLosses": 2,
      "roadPoints": 6,
      "roadRegulationPlusOtWins": 1,
      "roadRegulationWins": 0,
      "roadTies": 0,
      "roadWins": 2,
      "seasonId": 20252026,
      "shootoutLosses": 0,
      "shootoutWins": 2,
      "streakCode": "L",
      "streakCount": 1,
      "teamName": {
        "default": "Buffalo Sabres",
        "fr": "Sabres de Buffalo"
      },
      "teamCommonName": {
        "default": "Sabres"
      },
      "teamAbbrev": {
        "default": "BUF"
      },
      "teamLogo": "https://assets.nhle.com/logos/nhl/svg/BUF_light.svg",
      "ties": 0,
      "waiversSequence": 5,
      "wildcardSequence": 10,
      "winPctg": 0.407407,
      "wins": 11
    },
    {
      "conferenceAbbrev": "W",
      "conferenceHomeSequence": 11,
      "conferenceL10Sequence": 13,
      "conferenceName": "Western",
      "conferenceRoadSequence": 14,
      "conferenceSequence": 13,
      "date": "2025-12-04",
      "divisionAbbrev": "C",
      "divisionHomeSequence": 6,
      "divisionL10Sequence": 6,
      "divisionName": "Central",
      "divisionRoadSequence": 7,
      "divisionSequence": 7,
      "gameTypeId": 2,
      "gamesPlayed": 28,
      "goalDifferential": -29,
      "goalDifferentialPctg": -1.035714,
      "goalAgainst": 100,
      "goalFor": 71,
      "goalsForPctg": 2.535714,
      "homeGamesPlayed": 15,
      "homeGoalDifferential": -20,
      "homeGoalsAgainst": 57,
      "homeGoalsFor": 37,
      "homeLosses": 6,
      "homeOtLosses": 4,
      "homePoints": 14,
      "homeRegulationPlusOtWins": 5,
      "homeRegulationWins": 5,
      "homeTies": 0,
      "homeWins": 5,
      "l10GamesPlayed": 10,
      "l10GoalDifferential": -10,
      "l10GoalsAgainst": 29,
      "l10GoalsFor": 19,
      "l10Losses": 4,
      "l10OtLosses": 3,
      "l10Points": 9,
      "l10RegulationPlusOtWins": 3,
      "l10RegulationWins": 3,
      "l10Ties": 0,
      "l10Wins": 3,
      "leagueHomeSequence": 26,
      "leagueL10Sequence": 28,
      "leagueRoadSequence": 27,
      "leagueSequence": 29,
      "losses": 12,
      "otLosses": 7,
      "placeName": {
        "default": "St. Louis"
      },
      "pointPctg": 0.446429,
      "points": 25,
      "regulationPlusOtWinPctg": 0.321429,
      "regulationPlusOtWins": 9,
      "regulationWinPctg": 0.321429,
      "regulationWins": 9,
      "roadGamesPlayed": 13,
      "roadGoalDifferential": -9,
      "roadGoalsAgainst": 43,
      "roadGoalsFor": 34,
      "roadLosses": 6,
      "roadOtLosses": 3,
      "roadPoints": 11,
      "roadRegulationPlusOtWins": 4,
      "roadRegulationWins": 4,
      "roadTies": 0,
      "roadWins": 4,
      "seasonId": 20252026,
      "shootoutLosses": 2,
      "shootoutWins": 0,
      "streakCode": "L",
      "streakCount": 2,
      "teamName": {
        "default": "St. Louis Blues",
        "fr": "Blues de St. Louis"
      },
      "teamCommonName": {
        "default": "Blues"
      },
      "teamAbbrev": {
        "default": "STL"
      },
      "teamLogo": "https://assets.nhle.com/logos/nhl/svg/STL_light.svg?season=20252026",
      "ties": 0,
      "waiversSequence": 4,
      "wildcardSequence": 7,
      "winPctg": 0.321429,
      "wins": 9
    },
    {
      "conferenceAbbrev": "W",
      "conferenceHomeSequence": 12,
      "conferenceL10Sequence": 8,
      "conferenceName": "Western",
      "conferenceRoadSequence": 15,
      "conferenceSequence": 14,
      "date": "2025-12-04",
      "divisionAbbrev": "C",
      "divisionHomeSequence": 7,
      "divisionL10Sequence": 5,
      "divisionName": "Central",
      "divisionRoadSequence": 8,
      "divisionSequence": 8,
      "gameTypeId": 2,
      "gamesPlayed": 27,
      "goalDifferential": -23,
      "goalDifferentialPctg": -0.851852,
      "goalAgainst": 94,
      "goalFor": 71,
      "goalsForPctg": 2.62963,
      "homeGamesPlayed": 16,
      "homeGoalDifferential": -13,
      "homeGoalsAgainst": 55,
      "homeGoalsFor": 42,
      "homeLosses": 8,
      "homeOtLosses": 2,
      "homePoints": 14,
      "homeRegulationPlusOtWins": 5,
      "homeRegulationWins": 4,
      "homeTies": 0,
      "homeWins": 6,
      "l10GamesPlayed": 10,
      "l10GoalDifferential": -8,
      "l10GoalsAgainst": 35,
      "l10GoalsFor": 27,
      "l10Losses": 5,
      "l10OtLosses": 0,
      "l10Points": 10,
      "l10RegulationPlusOtWins": 5,
      "l10RegulationWins": 3,
      "l10Ties": 0,
      "l10Wins": 5,
      "leagueHomeSequence": 27,
      "leagueL10Sequence": 19,
      "leagueRoadSequence": 28,
      "leagueSequence": 30,
      "losses": 13,
      "otLosses": 4,
      "placeName": {
        "default": "Nashville"
      },
      "pointPctg": 0.444444,
      "points": 24,
      "regulationPlusOtWinPctg": 0.333333,
      "regulationPlusOtWins": 9,
      "regulationWinPctg": 0.259259,
      "regulationWins": 7,
      "roadGamesPlayed": 11,
      "roadGoalDifferential": -10,
      "roadGoalsAgainst": 39,
      "roadGoalsFor": 29,
      "roadLosses": 5,
      "roadOtLosses": 2,
      "roadPoints": 10,
      "roadRegulationPlusOtWins": 4,
      "roadRegulationWins": 3,
      "roadTies": 0,
      "roadWins": 4,
      "seasonId": 20252026,
      "shootoutLosses": 0,
      "shootoutWins": 1,
      "streakCode": "W",
      "streakCount": 2,
      "teamName": {
        "default": "Nashville Predators",
        "fr": "Predators de Nashville"
      },
      "teamCommonName": {
        "default": "Predators"
      },
      "teamAbbrev": {
        "default": "NSH"
      },
      "teamLogo": "https://assets.nhle.com/logos/nhl/svg/NSH_light.svg",
      "ties": 0,
      "waiversSequence": 3,
      "wildcardSequence": 8,
      "winPctg": 0.37037,
      "wins": 10
    },
    {
      "conferenceAbbrev": "W",
      "conferenceHomeSequence": 14,
      "conferenceL10Sequence": 5,
      "conferenceName": "Western",
      "conferenceRoadSequence": 13,
      "conferenceSequence": 15,
      "date": "2025-12-04",
      "divisionAbbrev": "P",
      "divisionHomeSequence": 6,
      "divisionL10Sequence": 2,
      "divisionName": "Pacific",
      "divisionRoadSequence": 7,
      "divisionSequence": 7,
      "gameTypeId": 2,
      "gamesPlayed": 29,
      "goalDifferential": -18,
      "goalDifferentialPctg": -0.62069,
      "goalAgainst": 88,
      "goalFor": 70,
      "goalsForPctg": 2.413793,
      "homeGamesPlayed": 11,
      "homeGoalDifferential": 3,
      "homeGoalsAgainst": 25,
      "homeGoalsFor": 28,
      "homeLosses": 4,
      "homeOtLosses": 2,
      "homePoints": 12,
      "homeRegulationPlusOtWins": 4,
      "homeRegulationWins": 4,
      "homeTies": 0,
      "homeWins": 5,
      "l10GamesPlayed": 10,
      "l10GoalDifferential": 0,
      "l10GoalsAgainst": 30,
      "l10GoalsFor": 30,
      "l10Losses": 3,
      "l10OtLosses": 2,
      "l10Points": 12,
      "l10RegulationPlusOtWins": 4,
      "l10RegulationWins": 4,
      "l10Ties": 0,
      "l10Wins": 5,
      "leagueHomeSequence": 29,
      "leagueL10Sequence": 10,
      "leagueRoadSequence": 26,
      "leagueSequence": 31,
      "losses": 15,
      "otLosses": 4,
      "placeName": {
        "default": "Calgary"
      },
      "pointPctg": 0.413793,
      "points": 24,
      "regulationPlusOtWinPctg": 0.275862,
      "regulationPlusOtWins": 8,
      "regulationWinPctg": 0.275862,
      "regulationWins": 8,
      "roadGamesPlayed": 18,
      "roadGoalDifferential": -21,
      "roadGoalsAgainst": 63,
      "roadGoalsFor": 42,
      "roadLosses": 11,
      "roadOtLosses": 2,
      "roadPoints": 12,
      "roadRegulationPlusOtWins": 4,
      "roadRegulationWins": 4,
      "roadTies": 0,
      "roadWins": 5,
      "seasonId": 20252026,
      "shootoutLosses": 2,
      "shootoutWins": 2,
      "streakCode": "W",
      "streakCount": 1,
      "teamName": {
        "default": "Calgary Flames",
        "fr": "Flames de Calgary"
      },
      "teamCommonName": {
        "default": "Flames"
      },
      "teamAbbrev": {
        "default": "CGY"
      },
      "teamLogo": "https://assets.nhle.com/logos/nhl/svg/CGY_light.svg",
      "ties": 0,
      "waiversSequence": 1,
      "wildcardSequence": 9,
      "winPctg": 0.344828,
      "wins": 10
    },
    {
      "conferenceAbbrev": "W",
      "conferenceHomeSequence": 16,
      "conferenceL10Sequence": 16,
      "conferenceName": "Western",
      "conferenceRoadSequence": 4,
      "conferenceSequence": 16,
      "date": "2025-12-04",
      "divisionAbbrev": "P",
      "divisionHomeSequence": 8,
      "divisionL10Sequence": 8,
      "divisionName": "Pacific",
      "divisionRoadSequence": 2,
      "divisionSequence": 8,
      "gameTypeId": 2,
      "gamesPlayed": 27,
      "goalDifferential": -18,
      "goalDifferentialPctg": -0.666667,
      "goalAgainst": 98,
      "goalFor": 80,
      "goalsForPctg": 2.962963,
      "homeGamesPlayed": 11,
      "homeGoalDifferential": -11,
      "homeGoalsAgainst": 42,
      "homeGoalsFor": 31,
      "homeLosses": 7,
      "homeOtLosses": 1,
      "homePoints": 7,
      "homeRegulationPlusOtWins": 3,
      "homeRegulationWins": 2,
      "homeTies": 0,
      "homeWins": 3,
      "l10GamesPlayed": 10,
      "l10GoalDifferential": -10,
      "l10GoalsAgainst": 40,
      "l10GoalsFor": 30,
      "l10Losses": 6,
      "l10OtLosses": 2,
      "l10Points": 6,
      "l10RegulationPlusOtWins": 2,
      "l10RegulationWins": 2,
      "l10Ties": 0,
      "l10Wins": 2,
      "leagueHomeSequence": 31,
      "leagueL10Sequence": 32,
      "leagueRoadSequence": 13,
      "leagueSequence": 32,
      "losses": 14,
      "otLosses": 3,
      "placeName": {
        "default": "Vancouver"
      },
      "pointPctg": 0.425926,
      "points": 23,
      "regulationPlusOtWinPctg": 0.296296,
      "regulationPlusOtWins": 8,
      "regulationWinPctg": 0.222222,
      "regulationWins": 6,
      "roadGamesPlayed": 16,
      "roadGoalDifferential": -7,
      "roadGoalsAgainst": 56,
      "roadGoalsFor": 49,
      "roadLosses": 7,
      "roadOtLosses": 2,
      "roadPoints": 16,
      "roadRegulationPlusOtWins": 5,
      "roadRegulationWins": 4,
      "roadTies": 0,
      "roadWins": 7,
      "seasonId": 20252026,
      "shootoutLosses": 0,
      "shootoutWins": 2,
      "streakCode": "L",
      "streakCount": 1,
      "teamName": {
        "default": "Vancouver Canucks",
        "fr": "Canucks de Vancouver"
      },
      "teamCommonName": {
        "default": "Canucks"
      },
      "teamAbbrev": {
        "default": "VAN"
      },
      "teamLogo": "https://assets.nhle.com/logos/nhl/svg/VAN_light.svg",
      "ties": 0,
      "waiversSequence": 2,
      "wildcardSequence": 10,
      "winPctg": 0.37037,
      "wins": 10
    }
  ]
}